machineio/__init__.py
machineio/condition.py
machineio/device.py
machineio/flags.py
machineio/group.py
machineio/pin.py
machineio/safety.py
machineio/tests.py
machineio/tools.py
machineio/drivers/__init__.py
machineio/drivers/firmata.py
machineio/drivers/raspberry_pi.py
machineio/drivers/test.py
machineio-0.8.0.dist-info/LICENCE
machineio-0.8.0.dist-info/METADATA
machineio-0.8.0.dist-info/WHEEL
machineio-0.8.0.dist-info/top_level.txt
machineio-0.8.0.dist-info/RECORD
