Metadata-Version: 2.1
Name: machineio
Version: 0.8.0
Summary: Machine and robotics gpio hardware interface creation toolkit.
Home-page: https://github.com/RobotZapa/machineio
Author: Michael Elliott
Author-email: robotzapa@gmail.com
License: UNKNOWN
Platform: UNKNOWN
Classifier: Programming Language :: Python :: 3.6
Classifier: Topic :: Scientific/Engineering :: Interface Engine/Protocol Translator
Classifier: License :: OSI Approved :: MIT License
Classifier: Operating System :: OS Independent
Classifier: Development Status :: 4 - Beta
Classifier: Framework :: Robot Framework
